grimpfunc/Flowlines.py
grimpfunc/GrIMPSubsetter.py
grimpfunc/NASALogin.py
grimpfunc/__init__.py
grimpfunc/boxPicker.py
grimpfunc/cmr.py
grimpfunc/cmrUrls.py
grimpfunc/pointInspector.py
grimpfunc-0.0.5.dist-info/METADATA
grimpfunc-0.0.5.dist-info/WHEEL
grimpfunc-0.0.5.dist-info/RECORD
