Metadata-Version: 2.3
Name: grimpfunc
Version: 0.0.5
Summary: SAR processing on the Cloud
License: MIT
Keywords: SAR,NSIDC,Holoviz
Author: Ian Joughin
Author-email: ian@apl.washington.edu
Requires-Python: >=3.8,<4.0
Classifier: License :: OSI Approved :: MIT License
Classifier: Programming Language :: Python :: 3
Classifier: Programming Language :: Python :: 3.8
Classifier: Programming Language :: Python :: 3.9
Classifier: Programming Language :: Python :: 3.10
Classifier: Programming Language :: Python :: 3.11
Classifier: Programming Language :: Python :: 3.12
Classifier: Programming Language :: Python :: 3.13
Requires-Dist: dask (>=2021)
Requires-Dist: holoviews (>=1,<2)
Requires-Dist: hvplot (>=0,<1)
Requires-Dist: numpy (>=1,<2)
Requires-Dist: pandas (>=1,<2)
Requires-Dist: panel (>=0,<1)
Requires-Dist: param (>=1,<2)
Requires-Dist: progressbar2 (>=3,<4)
Requires-Dist: pystac (>=1,<2)
Requires-Dist: requests (>=2,<3)
Requires-Dist: rio-stac (>=0,<1)
Requires-Dist: rioxarray (>=0,<1)
Requires-Dist: stackstac (>=0,<1)
Requires-Dist: xarray (>=0.20)
Project-URL: Homepage, https://github.com/fastice/grimpfunc
Project-URL: Repository, https://github.com/fastice/grimpfunc
